setup.py
pyidrac/__init__.py
pyidrac/geckodriver
pyidrac/pconf.py
pyidrac/phandle.py
pyidrac/pparse.py
pyidrac/precvinfo.py
pyidrac/pselenium.py
pyidrac/putil.py
pyidrac/setup.py
pyidrac.egg-info/PKG-INFO
pyidrac.egg-info/SOURCES.txt
pyidrac.egg-info/dependency_links.txt
pyidrac.egg-info/top_level.txt