Metadata-Version: 1.0
Name: pyidrac
Version: 0.1.4
Summary: pyidrac physical mechine info
Home-page: https://github.com/zhangliu520/pyidrac.git
Author: mrzl
Author-email: 752477168@qq.com
License: MIT Licence
Keywords: pip,pyidrac
Platform: any
